django_gcp/__init__.py
django_gcp/apps.py
django_gcp/exceptions.py
django_gcp/signals.py
django_gcp/urls.py
django_gcp/events/__init__.py
django_gcp/events/signals.py
django_gcp/events/utils.py
django_gcp/events/views.py
django_gcp/logs/__init__.py
django_gcp/logs/error_reporting.py
django_gcp/logs/structured_logs.py
django_gcp/management/__init__.py
django_gcp/management/commands/__init__.py
django_gcp/management/commands/_base.py
django_gcp/management/commands/cleanup_tmp_files.py
django_gcp/management/commands/task_manager.py
django_gcp/metadata/__init__.py
django_gcp/metadata/metadata.py
django_gcp/static/django_gcp/cloud_object_widget.css
django_gcp/static/django_gcp/cloud_object_widget.js
django_gcp/storage/__init__.py
django_gcp/storage/admin.py
django_gcp/storage/blob_utils.py
django_gcp/storage/compress.py
django_gcp/storage/fields.py
django_gcp/storage/forms.py
django_gcp/storage/gcloud.py
django_gcp/storage/operations.py
django_gcp/storage/settings.py
django_gcp/storage/utils.py
django_gcp/storage/widgets.py
django_gcp/tasks/__init__.py
django_gcp/tasks/helpers.py
django_gcp/tasks/manager.py
django_gcp/tasks/serializers.py
django_gcp/tasks/tasks.py
django_gcp/tasks/views.py
django_gcp/tasks/_pilot/__init__.py
django_gcp/tasks/_pilot/base.py
django_gcp/tasks/_pilot/exceptions.py
django_gcp/tasks/_pilot/mocker.py
django_gcp/tasks/_pilot/pubsub.py
django_gcp/tasks/_pilot/resource.py
django_gcp/tasks/_pilot/scheduler.py
django_gcp/tasks/_pilot/tasks.py
django_gcp/templates/django_gcp/cloud_object_widget.html
django_gcp/templates/unfold/contrib/django_gcp/cloud_object_readonly_widget.html
django_gcp/templates/unfold/contrib/django_gcp/cloud_object_widget.html
django_gcp/workflows/__init__.py
django_gcp/workflows/exceptions.py
django_gcp/workflows/workflows.py
django_gcp-0.22.3.dist-info/licenses/LICENSE
django_gcp-0.22.3.dist-info/METADATA
django_gcp-0.22.3.dist-info/WHEEL
django_gcp-0.22.3.dist-info/top_level.txt
django_gcp-0.22.3.dist-info/RECORD
