Metadata-Version: 2.4
Name: django-gcp
Version: 0.22.3
Summary: Utilities to run Django on Google Cloud Platform
Author: Tom Clark
License-Expression: MIT
Project-URL: Changelog, https://github.com/octue/django-gcp/releases
Project-URL: Documentation, https://django-gcp.readthedocs.io/
Project-URL: Homepage, https://github.com/octue/django-gcp
Project-URL: Issues, https://github.com/octue/django-gcp/issues
Project-URL: Repository, https://github.com/octue/django-gcp
Keywords: django,google,cloud,run,gcloud,gcp,storage,tasks,events,pubsub
Classifier: Development Status :: 5 - Production/Stable
Classifier: Intended Audience :: Developers
Classifier: Topic :: Software Development :: Libraries :: Python Modules
Classifier: Programming Language :: Python :: 3.10
Classifier: Programming Language :: Python :: 3.11
Classifier: Programming Language :: Python :: 3.12
Classifier: Programming Language :: Python :: 3.13
Classifier: Operating System :: OS Independent
Requires-Python: <4,>=3.10
License-File: LICENSE
Requires-Dist: Django<5.1,>=4.0
Requires-Dist: django-app-settings<0.8,>0.7
Requires-Dist: python-dateutil<3,>=2
Requires-Dist: google-api-python-client<3,>=2
Requires-Dist: google-auth<3,>=2.6
Requires-Dist: google-cloud-error-reporting<2,>=1.9
Requires-Dist: google-cloud-pubsub<3,>=2
Requires-Dist: google-cloud-scheduler<3,>=2
Requires-Dist: google-cloud-storage<4,>=2
Requires-Dist: google-cloud-tasks<3,>=2
Requires-Dist: google-cloud-workflows<2,>=1
Requires-Dist: werkzeug<4,>=3
Requires-Dist: pyopenssl<26,>=25.1
Dynamic: license-file
